{"DelieverMatrix":[{"walking":[false,false,false,false,false]}],"PriorAntiMatrix":[{"priorAnti":[false,false,false,false,false,false]}],"date":"2019-07-22","pooling":false,"postStepsMatrix":[{"steps":[null,209,14,40,76]},{"steps":[545,146,131,113,7]},{"steps":[451,174,46,161,47]},{"steps":[790,911,429,192,108]},{"steps":[466,194,352,47,518]},{"steps":[1196,776,72,108,0]},{"steps":[301,289,546,87,34]}],"preStepsMatrix":[{"steps":[184,106,513,193,129]},{"steps":[205,306,393,124,121]},{"steps":[425,270,151,183,361]},{"steps":[566,670,2223,93,383]},{"steps":[276,0,432,6,97]},{"steps":[405,1139,8,540,4]},{"steps":[1211,121,328,527,345]}],"totalStepsArray":[6281,8404,9585,12126,5827,10358,10524],"userID":"10110"}
