{"actionArray":[false,false,false,false,false],"appClick":18,"availabilityArray":[true,true,false,true,true],"date":"2019-09-21","lastActivity":false,"lastActivityArray":[false,false,false,false,false],"locationArray":[2,2,2,2,2],"postStepsArray":[400,507,299,227,39],"preStepsArray":[195,272,541,405,0],"priorAntiArray":[false,false,false,false,false,true],"probArray":[0.199251125360856,0.1,0,0.222782384462693,0.229289255880858],"studyDay":47,"temperatureArray":[16.1,17.65,20.16,18.79,17.57],"totalSteps":7285,"userID":"10137"}
