{"actionArray":[false,false,false,false,false],"appClick":0,"availabilityArray":[false,true,false,false,true],"date":"2019-08-13","lastActivity":false,"lastActivityArray":[false,false,false,false,false],"locationArray":[0,0,2,2,2],"postStepsArray":[776,191,28,46,100],"preStepsArray":[375,0,1037,94,41],"priorAntiArray":[false,false,false,false,false,false],"probArray":[0,0.445442679184675,0,0,0.392678332239055],"studyDay":40,"temperatureArray":[15.66,23.07,27,27.34,26.22],"totalSteps":16008,"userID":"10296"}
