{"actionArray":[false,false,false,false,false],"appClick":7,"availabilityArray":[false,true,false,true,true],"date":"2019-08-21","lastActivity":false,"lastActivityArray":[false,false,false,false,false],"locationArray":[1,1,1,1,1],"postStepsArray":[null,688,475,1702,15],"preStepsArray":[null,450,499,9,153],"priorAntiArray":[false,false,false,false,false,true],"probArray":[0,0.125091613252306,0,0.125117825011451,0.141694427759336],"studyDay":12,"temperatureArray":[22.59,29.36,30.36,29.55,25.82],"totalSteps":13491,"userID":"10342"}
