{"actionArray":[false,false,false,false,false],"appClick":42,"availabilityArray":[false,false,false,false,false],"date":"2019-09-17","lastActivity":false,"lastActivityArray":[false,false,false,false,false],"locationArray":[2,2,2,2,2],"postStepsArray":[null,null,null,null,null],"preStepsArray":[null,null,null,null,null],"priorAntiArray":[false,false,false,false,false,false],"probArray":[0,0,0,0,0],"studyDay":54,"temperatureArray":[12.71,14.91,16.71,15.26,13.06],"totalSteps":null,"userID":"10327"}
