{"actionArray":[false,true,false,false,true],"appClick":18,"availabilityArray":[false,true,false,false,true],"date":"2019-09-10","lastActivity":true,"lastActivityArray":[false,false,true,false,false],"locationArray":[0,0,0,2,2],"postStepsArray":[352,98,25,187,46],"preStepsArray":[1516,465,235,1160,32],"priorAntiArray":[false,true,false,true,false,false],"probArray":[0,0.8,0,0,0.733644881124906],"studyDay":88,"temperatureArray":[15.34,17.22,20.69,20.82,20.27],"totalSteps":17540,"userID":"10032"}
