{"actionArray":[false,false,false,false,false],"appClick":0,"availabilityArray":[false,false,false,false,false],"date":"2019-09-13","lastActivity":false,"lastActivityArray":[false,false,false,false,false],"locationArray":[2,2,2,2,2],"postStepsArray":[null,null,null,null,null],"preStepsArray":[null,null,null,null,null],"priorAntiArray":[false,false,false,false,false,false],"probArray":[0,0,0,0,0],"studyDay":99,"temperatureArray":[18.18,18.94,18.94,16.81,12.96],"totalSteps":null,"userID":"test-mash"}
